bytecode_nop = 0x00
bytecode_aconst_null = 0x01
bytecode_iconst_m1 = 0x02
bytecode_iconst_0 = 0x03
bytecode_iconst_1 = 0x04
bytecode_iconst_2 = 0x05
bytecode_iconst_3 = 0x06
bytecode_iconst_4 = 0x07
bytecode_iconst_5 = 0x08
bytecode_lconst_0 = 0x09
bytecode_lconst_1 = 0x0a
bytecode_fconst_0 = 0x0b
bytecode_fconst_1 = 0x0c
bytecode_fconst_2 = 0x0d
bytecode_dconst_0 = 0x0e
bytecode_dconst_1 = 0x0f
bytecode_bipush = 0x10
bytecode_sipush = 0x11
bytecode_ldc = 0x12
bytecode_ldc_w = 0x13
bytecode_ldc2_w = 0x14
bytecode_iload = 0x15
bytecode_lload = 0x16
bytecode_fload = 0x17
bytecode_dload = 0x18
bytecode_aload = 0x19
bytecode_iload_0 = 0x1a
bytecode_iload_1 = 0x1b
bytecode_iload_2 = 0x1c
bytecode_iload_3 = 0x1d
bytecode_lload_0 = 0x1e
bytecode_lload_1 = 0x1f
bytecode_lload_2 = 0x20
bytecode_lload_3 = 0x21
bytecode_fload_0 = 0x22
bytecode_fload_1 = 0x23
bytecode_fload_2 = 0x24
bytecode_fload_3 = 0x25
bytecode_dload_0 = 0x26
bytecode_dload_1 = 0x27
bytecode_dload_2 = 0x28
bytecode_dload_3 = 0x29
bytecode_aload_0 = 0x2a
bytecode_aload_1 = 0x2b
bytecode_aload_2 = 0x2c
bytecode_aload_3 = 0x2d
bytecode_iaload = 0x2e
bytecode_laload = 0x2f
bytecode_faload = 0x30
bytecode_daload = 0x31
bytecode_aaload = 0x32
bytecode_baload = 0x33
bytecode_caload = 0x34
bytecode_saload = 0x35
bytecode_istore = 0x36
bytecode_lstore = 0x37
bytecode_fstore = 0x38
bytecode_dstore = 0x39
bytecode_astore = 0x3a
bytecode_istore_0 = 0x3b
bytecode_istore_1 = 0x3c
bytecode_istore_2 = 0x3d
bytecode_istore_3 = 0x3e
bytecode_lstore_0 = 0x3f
bytecode_lstore_1 = 0x40
bytecode_lstore_2 = 0x41
bytecode_lstore_3 = 0x42
bytecode_fstore_0 = 0x43
bytecode_fstore_1 = 0x44
bytecode_fstore_2 = 0x45
bytecode_fstore_3 = 0x46
bytecode_dstore_0 = 0x47
bytecode_dstore_1 = 0x48
bytecode_dstore_2 = 0x49
bytecode_dstore_3 = 0x4a
bytecode_astore_0 = 0x4b
bytecode_astore_1 = 0x4c
bytecode_astore_2 = 0x4d
bytecode_astore_3 = 0x4e
bytecode_iastore = 0x4f
bytecode_lastore = 0x50
bytecode_fastore = 0x51
bytecode_dastore = 0x52
bytecode_aastore = 0x53
bytecode_bastore = 0x54
bytecode_castore = 0x55
bytecode_sastore = 0x56
bytecode_pop = 0x57
bytecode_pop2 = 0x58
bytecode_dup = 0x59
bytecode_dup_x1 = 0x5a
bytecode_dup_x2 = 0x5b
bytecode_dup2 = 0x5c
bytecode_dup2_x1 = 0x5d
bytecode_dup2_x2 = 0x5e
bytecode_swap = 0x5f
bytecode_iadd = 0x60
bytecode_ladd = 0x61
bytecode_fadd = 0x62
bytecode_dadd = 0x63
bytecode_isub = 0x64
bytecode_lsub = 0x65
bytecode_fsub = 0x66
bytecode_dsub = 0x67
bytecode_imul = 0x68
bytecode_lmul = 0x69
bytecode_fmul = 0x6a
bytecode_dmul = 0x6b
bytecode_idiv = 0x6c
bytecode_ldiv = 0x6d
bytecode_fdiv = 0x6e
bytecode_ddiv = 0x6f
bytecode_irem = 0x70
bytecode_lrem = 0x71
bytecode_frem = 0x72
bytecode_drem = 0x73
bytecode_ineg = 0x74
bytecode_lneg = 0x75
bytecode_fneg = 0x76
bytecode_dneg = 0x77
bytecode_ishl = 0x78
bytecode_lshl = 0x79
bytecode_ishr = 0x7a
bytecode_lshr = 0x7b
bytecode_iushr = 0x7c
bytecode_lushr = 0x7d
bytecode_iand = 0x7e
bytecode_land = 0x7f
bytecode_ior = 0x80
bytecode_lor = 0x81
bytecode_ixor = 0x82
bytecode_lxor = 0x83
bytecode_iinc = 0x84
bytecode_i2l = 0x85
bytecode_i2f = 0x86
bytecode_i2d = 0x87
bytecode_l2i = 0x88
bytecode_l2f = 0x89
bytecode_l2d = 0x8a
bytecode_f2i = 0x8b
bytecode_f2l = 0x8c
bytecode_f2d = 0x8d
bytecode_d2i = 0x8e
bytecode_d2l = 0x8f
bytecode_d2f = 0x90
bytecode_i2b = 0x91
bytecode_i2c = 0x92
bytecode_i2s = 0x93
bytecode_lcmp = 0x94
bytecode_fcmpl = 0x95
bytecode_fcmpg = 0x96
bytecode_dcmpl = 0x97
bytecode_dcmpg = 0x98
bytecode_ifeq = 0x99
bytecode_ifne = 0x9a
bytecode_iflt = 0x9b
bytecode_ifge = 0x9c
bytecode_ifgt = 0x9d
bytecode_ifle = 0x9e
bytecode_if_icmpeq = 0x9f
bytecode_if_icmpne = 0xa0
bytecode_if_icmplt = 0xa1
bytecode_if_icmpge = 0xa2
bytecode_if_icmpgt = 0xa3
bytecode_if_icmple = 0xa4
bytecode_if_acmpeq = 0xa5
bytecode_if_acmpne = 0xa6
bytecode_getstatic = 0xb2
bytecode_putstatic = 0xb3
bytecode_getfield = 0xb4
bytecode_putfield = 0xb5
bytecode_invokevirtual = 0xb6
bytecode_invokespecial = 0xb7
bytecode_invokestatic = 0xb8
bytecode_invokeinterface = 0xb9
bytecode_invokedynamic = 0xba
bytecode_new = 0xbb
bytecode_newarray = 0xbc
bytecode_anewarray = 0xbd
bytecode_arraylength = 0xbe
bytecode_athrow = 0xbf
bytecode_checkcast = 0xc0
bytecode_instanceof = 0xc1
bytecode_monitorenter = 0xc2
bytecode_monitorexit = 0xc3
bytecode_goto = 0xa7
bytecode_jsr = 0xa8
bytecode_ret = 0xa9
bytecode_tableswitch = 0xaa
bytecode_lookupswitch = 0xab
bytecode_ireturn = 0xac
bytecode_lreturn = 0xad
bytecode_freturn = 0xae
bytecode_dreturn = 0xaf
bytecode_areturn = 0xb0
bytecode_return = 0xb1
bytecode_wide = 0xc4
bytecode_multianewarray = 0xc5
bytecode_ifnull = 0xc6
bytecode_ifnonnull = 0xc7
bytecode_goto_w = 0xc8
bytecode_jsr_w = 0xc9
bytecode_breakpoint = 0xca
bytecode_impdep1 = 0xfe
bytecode_impdep2 = 0xff